emogen/__init__.py
emogen-0.0.1.dist-info/METADATA
emogen-0.0.1.dist-info/WHEEL
emogen-0.0.1.dist-info/licenses/LICENSE.txt
emogen-0.0.1.dist-info/RECORD
