Metadata-Version: 2.4
Name: emogen
Version: 0.0.1
Summary: A Python library for generating emotions.
Project-URL: Documentation, https://github.com/Yasas Senarath/emogen#readme
Project-URL: Issues, https://github.com/Yasas Senarath/emogen/issues
Project-URL: Source, https://github.com/Yasas Senarath/emogen
Author-email: Yasas Senarath <12231659+ysenarath@users.noreply.github.com>
License-Expression: MIT
License-File: LICENSE.txt
Classifier: Development Status :: 4 - Beta
Classifier: Programming Language :: Python
Classifier: Programming Language :: Python :: 3.9
Classifier: Programming Language :: Python :: 3.10
Classifier: Programming Language :: Python :: 3.11
Classifier: Programming Language :: Python :: 3.12
Classifier: Programming Language :: Python :: Implementation :: CPython
Classifier: Programming Language :: Python :: Implementation :: PyPy
Requires-Python: >=3.9
